yaqd_thorlabs/VERSION
yaqd_thorlabs/__init__.py
yaqd_thorlabs/__version__.py
yaqd_thorlabs/_serial.py
yaqd_thorlabs/_thorlabs_apt_motor.py
yaqd_thorlabs/_thorlabs_bsc201.py
yaqd_thorlabs/_thorlabs_bsc203.py
yaqd_thorlabs/_thorlabs_ell18.py
yaqd_thorlabs/_thorlabs_ellx.py
yaqd_thorlabs/_thorlabs_k10cr1.py
yaqd_thorlabs/_thorlabs_kdc101.py
yaqd_thorlabs/_thorlabs_kst101.py
yaqd_thorlabs/_thorlabs_lts150.py
yaqd_thorlabs/_thorlabs_lts300.py
yaqd_thorlabs/_thorlabs_mpc320.py
yaqd_thorlabs/_thorlabs_pax1000.py
yaqd_thorlabs/_thorlabs_pm_triggered.py
yaqd_thorlabs/thorlabs-bsc201.avpr
yaqd_thorlabs/thorlabs-bsc201.toml
yaqd_thorlabs/thorlabs-bsc203.avpr
yaqd_thorlabs/thorlabs-bsc203.toml
yaqd_thorlabs/thorlabs-ell18.avpr
yaqd_thorlabs/thorlabs-ell18.toml
yaqd_thorlabs/thorlabs-k10cr1.avpr
yaqd_thorlabs/thorlabs-k10cr1.toml
yaqd_thorlabs/thorlabs-kdc101.avpr
yaqd_thorlabs/thorlabs-kdc101.toml
yaqd_thorlabs/thorlabs-kst101.avpr
yaqd_thorlabs/thorlabs-kst101.toml
yaqd_thorlabs/thorlabs-lts150.avpr
yaqd_thorlabs/thorlabs-lts150.toml
yaqd_thorlabs/thorlabs-lts300.avpr
yaqd_thorlabs/thorlabs-lts300.toml
yaqd_thorlabs/thorlabs-mpc320.avpr
yaqd_thorlabs/thorlabs-mpc320.toml
yaqd_thorlabs/thorlabs-pax1000.avpr
yaqd_thorlabs/thorlabs-pax1000.toml
yaqd_thorlabs/thorlabs-pm-triggered.avpr
yaqd_thorlabs/thorlabs-pm-triggered.toml
yaqd_thorlabs-2022.7.0.dist-info/entry_points.txt
yaqd_thorlabs-2022.7.0.dist-info/LICENSE
yaqd_thorlabs-2022.7.0.dist-info/WHEEL
yaqd_thorlabs-2022.7.0.dist-info/METADATA
yaqd_thorlabs-2022.7.0.dist-info/RECORD
