Metadata-Version: 2.1
Name: yaqd-thorlabs
Version: 2022.7.0
Summary: yaq daemons for thorlabs hardware
Home-page: https://yaq.fyi
Author: yaq Developers
Author-email: git@ksunden.space
Requires-Python: >=3.7
Classifier: Development Status :: 4 - Beta
Classifier: Intended Audience :: Science/Research
Classifier: License :: OSI Approved :: GNU Lesser General Public License v3 (LGPLv3)
Classifier: Natural Language :: English
Classifier: Programming Language :: Python :: 3
Classifier: Programming Language :: Python :: 3.7
Classifier: Programming Language :: Python :: 3.8
Classifier: Topic :: Scientific/Engineering
Requires-Dist: yaqd-core>=2020.10.1
Requires-Dist: thorlabs-apt-protocol>=29.0.0
Requires-Dist: pyserial
Requires-Dist: pyvisa
Requires-Dist: pyvisa-py
Requires-Dist: pyusb
Requires-Dist: black ; extra == "dev"
Requires-Dist: pre-commit ; extra == "dev"
Project-URL: Issues, https://github.com/yaq-project/yaqd-thorlabs/issues
Project-URL: Source, https://github.com/yaq-project/yaqd-thorlabs
Provides-Extra: dev
